{"years_2023.md":"BfgkmbyE","columns_6964382482007490590.md":"BeIgpPHZ","years_2021.md":"DBcNVDHW","categories_6809637776263217160.md":"BhKaxRFB","years_2020.md":"eW0aSaLm","columns_7151965181705191460.md":"BEr0VwAz","columns_7202898170614595645.md":"Bja3IyL0","columns_index.md":"CDITNSrM","index.md":"DDQrCjnT","columns_7127148104792408077.md":"CIQvqNsb","columns_7136858810605371399.md":"CddCLyd-","years_2024.md":"BDXb1x36","categories_6809637767543259144.md":"BuIIswOO","ranking_index.md":"C2acwLqk","columns_7151964821137653773.md":"lYnrIemN","years_2022.md":"DqNJL9OH","categories_6809637772874219534.md":"BX1c0R8A","overview_index.md":"DaOA5FPW","columns_7124950036349190174.md":"CJEnF5bi","categories_index.md":"xybuUs7G"}
