{"categories_index.md":"BCCjzLkW","categories_6809637772874219534.md":"BV6oHVfw","years_2020.md":"CUJTTIsA","columns_7151964821137653773.md":"DU_yeMYA","categories_6809637776263217160.md":"Ddgjx9wb","columns_7136858810605371399.md":"CKGk1uEP","columns_7151965181705191460.md":"CkmIm3we","index.md":"Bht38zU5","columns_index.md":"DY84PxGR","columns_7124950036349190174.md":"C2VVUZuf","years_2024.md":"B8xrh75a","columns_6964382482007490590.md":"CrxCPYKs","overview_index.md":"C3kaRXxQ","columns_7127148104792408077.md":"BBbEyN7T","years_2023.md":"DEdTtLa4","categories_6809637767543259144.md":"CBIv5uOq","columns_7202898170614595645.md":"D9N4MLE0","ranking_index.md":"DffKf0SZ","years_2021.md":"DtK6pZFL","years_2022.md":"BP19-0Nn"}
