{"categories_6809637767543259144.md":"B2XLc_-i","categories_6809637772874219534.md":"A-foJAGW","categories_6809637776263217160.md":"Cd8SGcnz","categories_index.md":"Sj1CzBGu","columns_6964382482007490590.md":"CRpCKPt3","columns_7124950036349190174.md":"DxA7SHV0","columns_7127148104792408077.md":"CCVV52O3","columns_7136858810605371399.md":"CrPA97gT","columns_7151964821137653773.md":"DbUzm1x5","columns_7151965181705191460.md":"DBUpfVie","columns_7202898170614595645.md":"1FMwJ8Gn","columns_7429243880883224626.md":"2pt09RCp","columns_index.md":"BPPPoK2j","index.md":"D1wh-TuL","overview_index.md":"BQBgsVDT","ranking_index.md":"CnGK3ALu","years_2020.md":"B09LaQwj","years_2021.md":"BpDLFvbR","years_2022.md":"BMVyZ82s","years_2023.md":"DtrQ6FZv","years_2024.md":"DurM9GBb"}
