{"categories_6809637767543259144.md":"DMbnpW9o","categories_6809637772874219534.md":"BuSpWf09","categories_6809637776263217160.md":"BOwN8vfn","categories_index.md":"DaSxJZNQ","columns_6964382482007490590.md":"CS06KGyv","columns_7124950036349190174.md":"B8JWnThl","columns_7127148104792408077.md":"BWPGaU7Z","columns_7136858810605371399.md":"CanRWHJb","columns_7151964821137653773.md":"Bjqyefo9","columns_7151965181705191460.md":"uCGyqfEI","columns_7202898170614595645.md":"CYn0AV1w","columns_index.md":"iV14ZKjl","index.md":"D1wh-TuL","overview_index.md":"epIHfGMs","ranking_index.md":"Cu0D2I-H","years_2020.md":"CQ9Lpy9a","years_2021.md":"OqUovwAT","years_2022.md":"ep4yTAgD","years_2023.md":"BbT5RH1q","years_2024.md":"D4RENslq"}
