{"columns_7151965181705191460.md":"D_5O7-kk","categories_6809637772874219534.md":"BV6oHVfw","index.md":"Bht38zU5","years_2021.md":"G8h3VxTs","columns_7127148104792408077.md":"fomUB23K","columns_7136858810605371399.md":"SOg1tW5Z","columns_6964382482007490590.md":"WRNu5quE","years_2020.md":"teB4FfhZ","categories_6809637776263217160.md":"Ddgjx9wb","categories_6809637767543259144.md":"DmZ0u77P","categories_index.md":"CGiXyXJJ","columns_7202898170614595645.md":"C3Oc1wZc","columns_index.md":"BJj_Emei","years_2023.md":"1jdkHUdq","ranking_index.md":"a3gUemMB","columns_7124950036349190174.md":"NXdcYIMc","years_2024.md":"ByzluM-N","columns_7151964821137653773.md":"DLLX4YW_","overview_index.md":"C3ooEKxI","years_2022.md":"32AB8XT7"}
